[
  {
    "image": "images/abelha.webp",
    "title": "Modelo do Zangão Abelha"
  },
  {
    "image": "images/abelha1.webp",
    "title": "Modelo do Zangão Abelha"
  },
  {
    "image": "images/dyst.webp",
    "title": "Modelo da Operária Dyst"
  },
  {
    "image": "images/dyst1.webp",
    "title": "Modelo da Operária Dyst"
  },
  {
    "image": "images/jay.webp",
    "title": "Modelo da Operária Jay"
  },
  {
    "image": "images/nokia.webp",
    "title": "Modelo do Zangão Nokia"
  },
  {
    "image": "images/omnix.webp",
    "title": "Modelo do Zangão Omnix"
  },
  {
    "image": "images/urso_pudim.webp",
    "title": "Modelo do Urso Pudim"
  },
  {
    "image": "images/wendy.webp",
    "title": "Modelo da Operária Wendy"
  },
  {
    "image": "images/loht.webp",
    "title": "Modelo do Zangão Loht"
  },
  {
    "image": "images/abelha2.webp",
    "title": "Modelo do Zangão Abelha"
  },
  {
    "image": "images/asher.webp",
    "title": "Modelo do Zangão Asher"
  },
  {
    "image": "images/faby.webp",
    "title": "Modelo da Operária Faby"
  },
  {
    "image": "images/faby1.webp",
    "title": "Modelo da Operária Faby"
  },
  {
    "image": "images/huvelly.webp",
    "title": "Modelo da Operária Huvelly"
  },
  {
    "image": "images/hunter.webp",
    "title": "Modelo do Zangão Hunter"
  },
  {
    "image": "images/ino.webp",
    "title": "Modelo do Zangão Ino"
  },
  {
    "image": "images/shark.webp",
    "title": "Modelo da Operária Shark"
  },
  {
    "image": "images/anjo.webp",
    "title": "Modelo do Zangão Anjo"
  },
  {
    "image": "images/sr_peeking.webp",
    "title": "Modelo do Zangão Sr Peeking"
  },
  {
    "image": "images/viannna.webp",
    "title": "Modelo do Zangão Viannna"
  },
  {
    "image": "images/kanguru.webp",
    "title": "Modelo do Zangão Kanguru"
  },
  {
    "image": "images/luca.webp",
    "title": "Modelo do Zangão Luca"
  },
  {
    "image": "images/kim.webp",
    "title": "Modelo do Zangão Kim"
  },
  {
    "image": "images/dazai.webp",
    "title": "Modelo do Zangão Dazai"
  },
  {
    "image": "images/milka.webp",
    "title": "Modelo da Operária Milka"
  },
  {
    "image": "images/neblai.webp",
    "title": "Modelo da Operária Neblai"
  },
  {
    "image": "images/sus.webp",
    "title": "Modelo da Operária Sus"
  },
  {
    "image": "images/aleph.png",
    "title": "Modelo do Zangão Aleph"
  },
  {
    "image": "images/buddha.png",
    "title": "Modelo do Zangão Buddha"
  },
  {
    "image": "images/caffe.png",
    "title": "Modelo do Zangão Caffe"
  },
  {
    "image": "images/caffe1.png",
    "title": "Modelo do Zangão Caffe"
  },
  {
    "image": "images/chapeu_da_fita_amarela.png",
    "title": "Modelo do Zangão Chapéu da Fita Amarela"
  },
  {
    "image": "images/coelha_maga.png",
    "title": "Modelo da Operária Coelha Maga"
  },
  {
    "image": "images/dazai1.png",
    "title": "Modelo do Zangão Dazai"
  },
  {
    "image": "images/demonia.png",
    "title": "Modelo da Operária Demonia"
  },
  {
    "image": "images/dragao_negro.png",
    "title": "Modelo do Zangão Dragão Negro"
  },
  {
    "image": "images/dragon.png",
    "title": "Modelo do Zangão Dragon"
  },
  {
    "image": "images/elfo_medico.png",
    "title": "Modelo do Zangão Elfo Médico"
  },
  {
    "image": "images/fadoooo.png",
    "title": "Modelo do Zangão Fadoooo"
  },
  {
    "image": "images/macaco_fant0n.png",
    "title": "Modelo do Zangão Macaco Fant0n"
  },
  {
    "image": "images/ratinho_lony.png",
    "title": "Modelo do Zangão Ratinho Lony"
  },
  {
    "image": "images/mel.png",
    "title": "Modelo do Zangão Mel"
  },
  {
    "image": "images/ninja_asas_negras.png",
    "title": "Modelo do Zangão Ninja Asas Negras"
  },
  {
    "image": "images/o_touro.png",
    "title": "Modelo do Zangão O Touro"
  },
  {
    "image": "images/olhos_de_anjo.png",
    "title": "Modelo da Operária Olhos de Anjo"
  },
  {
    "image": "images/omnix1.png",
    "title": "Modelo do Zangão Omnix"
  },
  {
    "image": "images/sonho_de_padaria_granulada.png",
    "title": "Modelo da Operária Sonho de Padaria Granulada"
  },
  {
    "image": "images/yuna.png",
    "title": "Modelo da Operária Yuna"
  }
]